godocs/__init__.py
godocs/py.typed
godocs/cli/__init__.py
godocs/cli/main.py
godocs/cli/command/__init__.py
godocs/cli/command/app_command.py
godocs/cli/command/cli_command.py
godocs/cli/command/contruct_command.py
godocs/constructor/__init__.py
godocs/constructor/constructor.py
godocs/constructor/mapper.py
godocs/parser/__init__.py
godocs/parser/context_creator.py
godocs/parser/xml_parser.py
godocs/plugin/__init__.py
godocs/plugin/loader.py
godocs/plugin/plugin.py
godocs/translation/__init__.py
godocs/translation/ast/__init__.py
godocs/translation/ast/node.py
godocs/translation/ast/tag_node.py
godocs/translation/ast/text_node.py
godocs/translation/interpreter/__init__.py
godocs/translation/interpreter/bbcode_interpreter.py
godocs/translation/interpreter/interpreter.py
godocs/translation/translator/__init__.py
godocs/translation/translator/mapper.py
godocs/translation/translator/rst_syntax_translator.py
godocs/translation/translator/syntax_translator.py
godocs/util/__init__.py
godocs/util/dir.py
godocs/util/module.py
godocs/util/options.py
godocs-0.2.1.dist-info/licenses/LICENSE
godocs-0.2.1.dist-info/METADATA
godocs-0.2.1.dist-info/WHEEL
godocs-0.2.1.dist-info/entry_points.txt
godocs-0.2.1.dist-info/top_level.txt
godocs-0.2.1.dist-info/RECORD
