Metadata-Version: 2.4
Name: godocs
Version: 0.2.1
Summary: CLI tool for converting Godot's XML docs into RST Markdown
Author-email: "Daniel Sousa (nadjiel)" <oliveira.daaaaniel@gmail.com>
License-Expression: MIT
Project-URL: Homepage, https://github.com/godocs-godot/godocs
Project-URL: Issues, https://github.com/godocs-godot/godocs/issues
Keywords: python,godot,documentation,docs,godocs,sphinx,jinja2
Classifier: Programming Language :: Python :: 3
Classifier: Operating System :: OS Independent
Classifier: Development Status :: 4 - Beta
Classifier: Intended Audience :: Developers
Classifier: Natural Language :: English
Requires-Python: >=3.0
License-File: LICENSE
Provides-Extra: dev
Requires-Dist: build; extra == "dev"
Requires-Dist: twine; extra == "dev"
Requires-Dist: pytest<9.0.0,>=8.4.1; extra == "dev"
Dynamic: license-file
